grid_royale/__init__.py
grid_royale/__main__.py
grid_royale/animating.py
grid_royale/commands.py
grid_royale/constants.py
grid_royale/core.py
grid_royale/demo.h5
grid_royale/vectoring.py
grid_royale/gamey/__init__.py
grid_royale/gamey/aggregating.py
grid_royale/gamey/base.py
grid_royale/gamey/exceptions.py
grid_royale/gamey/gaming.py
grid_royale/gamey/model_based.py
grid_royale/gamey/model_free.py
grid_royale/gamey/policing.py
grid_royale/gamey/sample_games/__init__.py
grid_royale/gamey/sample_games/blackjack.py
grid_royale/gamey/utils/__init__.py
grid_royale/gamey/utils/chain_space.py
grid_royale/gamey/utils/iterating.py
grid_royale/gamey/utils/nice_task_shower.py
grid_royale/gamey/utils/weak_key_identity_dict.py
grid_royale/server/__init__.py
grid_royale/server/server.py
grid_royale/server/frontend/grid_royale.html
grid_royale/server/frontend/grid_royale.js
grid_royale/server/frontend/grid_royale.py
grid_royale/server/frontend/pause.png
grid_royale/server/frontend/play.png
grid_royale/utils/__init__.py
grid_royale/utils/make_keras_picklable.py
grid_royale/utils/pycompat.py
grid_royale-0.3.0.dist-info/AUTHORS
grid_royale-0.3.0.dist-info/LICENSE
grid_royale-0.3.0.dist-info/METADATA
grid_royale-0.3.0.dist-info/WHEEL
grid_royale-0.3.0.dist-info/entry_points.txt
grid_royale-0.3.0.dist-info/top_level.txt
grid_royale-0.3.0.dist-info/RECORD
