Metadata-Version: 2.1
Name: grid-royale
Version: 0.3.0
Summary: GridRoyale - A life simulation for exploring social dynamics
Home-page: https://github.com/cool-RR/grid_royale
Author: Ram Rachum
Author-email: ram@rachum.com
License: UNKNOWN
Platform: UNKNOWN
Classifier: Intended Audience :: Developers
Classifier: Programming Language :: Python :: 3.8
Classifier: Programming Language :: Python :: 3.9
Classifier: Programming Language :: Python :: 3.10
Classifier: Programming Language :: Python :: Implementation :: CPython
Classifier: License :: OSI Approved :: MIT License
Classifier: Operating System :: OS Independent
Classifier: Topic :: Scientific/Engineering :: Artificial Intelligence
Classifier: Topic :: Scientific/Engineering :: Artificial Life
Requires-Python: >=3.8
Requires-Dist: Keras (>=2.4.3)
Requires-Dist: click (>=7.1.2)
Requires-Dist: flask (>=1.1.2)
Requires-Dist: h5py (==2.10.0)
Requires-Dist: immutabledict (>=1.0.0)
Requires-Dist: lru-dict (>=1.1.7)
Requires-Dist: more-itertools (>=8.7.0)
Requires-Dist: numpy
Requires-Dist: requests (>=2.25.1)
Requires-Dist: scipy (>=1.5.2)
Requires-Dist: tensorflow (==2.3.1)
Provides-Extra: tests
Requires-Dist: pytest ; extra == 'tests'
